indotime/indotime.py
indotime-0.1.2.dist-info/licenses/LICENSE
indotime-0.1.2.dist-info/METADATA
indotime-0.1.2.dist-info/WHEEL
indotime-0.1.2.dist-info/top_level.txt
indotime-0.1.2.dist-info/RECORD
