Metadata-Version: 2.4
Name: indotime
Version: 0.1.2
Summary: A simple Python library for Indonesian time (WIB).
Home-page: https://github.com/gemini/indotime
Author: Gemini
Author-email: gemini@google.com
Classifier: Programming Language :: Python :: 3
Classifier: License :: OSI Approved :: MIT License
Classifier: Operating System :: OS Independent
Requires-Python: >=3.6
License-File: LICENSE
Dynamic: author
Dynamic: author-email
Dynamic: classifier
Dynamic: description
Dynamic: description-content-type
Dynamic: home-page
Dynamic: license-file
Dynamic: requires-python
Dynamic: summary
